pyhaze.cp37-win_amd64.pyd
pyhaze-0.1.2.dist-info/LICENSE
pyhaze-0.1.2.dist-info/METADATA
pyhaze-0.1.2.dist-info/WHEEL
pyhaze-0.1.2.dist-info/top_level.txt
pyhaze-0.1.2.dist-info/RECORD
