Metadata-Version: 2.1
Name: pyhaze
Version: 0.1.2
Summary: Fast smoothing of per-vertex data on triangular meshes.
Home-page: https://github.com/dfsp-spirit/pyhaze
Author: Tim Schaefer
Author-email: Tim Schaefer <ts+code@rcmd.org>
License: MIT License
Project-URL: homepage, https://github.com/dfsp-spirit/pyhaze
Project-URL: documentation, https://github.com/dfsp-spirit/pyhaze
Project-URL: repository, https://github.com/dfsp-spirit/pyhaze
Keywords: mesh,triangular-mesh,smoothing,overlay,per-vertex data,mesh descriptor,haze,neuroimaging,MRI,brain
Classifier: Programming Language :: C++
Classifier: Programming Language :: Python :: 3 :: Only
Classifier: Programming Language :: Python :: 3.6
Classifier: Programming Language :: Python :: 3.7
Classifier: Programming Language :: Python :: 3.8
Classifier: Programming Language :: Python :: 3.9
Classifier: Programming Language :: Python :: 3.10
Classifier: Programming Language :: Python :: 3.11
Classifier: Programming Language :: Python :: Implementation :: CPython
Classifier: Programming Language :: Python :: Implementation :: PyPy
Classifier: License :: OSI Approved :: MIT License
Classifier: Development Status :: 3 - Alpha
Classifier: Intended Audience :: Science/Research
Classifier: Intended Audience :: Developers
Classifier: License :: OSI Approved :: MIT License
Classifier: Operating System :: POSIX :: Linux
Classifier: Operating System :: Microsoft :: Windows
Classifier: Operating System :: MacOS
Classifier: Natural Language :: English
License-File: LICENSE
